pywidgy/__init__.py
pywidgy/checkboxes.py
pywidgy/dialog.py
pywidgy/free_text.py
pywidgy/menu.py
pywidgy/runner.py
pywidgy/table.py
pywidgy/widget.py
pywidgy-0.1.2.dist-info/METADATA
pywidgy-0.1.2.dist-info/WHEEL
pywidgy-0.1.2.dist-info/RECORD
