Metadata-Version: 2.4
Name: pywidgy
Version: 0.1.2
Summary: A lightweight widget framework for Python terminal apps
Project-URL: Homepage, https://github.com/epersni/pywidgy
Author: Nicklas Persson
License-Expression: MIT
Requires-Python: >=3.9
Requires-Dist: blessed==1.20.0
